cbmc/__init__.py
cbmc/api.py
cbmc/exception.py
cbmc/post.py
tests/__init__.py
tests/test_api.py
tests/test_post.py
cbmc.py-0.0.4.dist-info/LICENSE
cbmc.py-0.0.4.dist-info/METADATA
cbmc.py-0.0.4.dist-info/WHEEL
cbmc.py-0.0.4.dist-info/top_level.txt
cbmc.py-0.0.4.dist-info/RECORD
