Metadata-Version: 2.1
Name: cbmc.py
Version: 0.0.4
Summary: An unofficial 麥塊匿名發文平台 API wrapper.
Home-page: https://github.com/ItsRqtl/cbmc.py
Author: ItsRqtl
Author-email: itsrql@gmail.com
License: MIT
Classifier: Development Status :: 4 - Beta
Classifier: License :: OSI Approved :: MIT License
Classifier: Operating System :: OS Independent
Classifier: Natural Language :: English
Classifier: Programming Language :: Python :: 3
Requires-Python: >=3.6
License-File: LICENSE
Requires-Dist: requests
Requires-Dist: aiohttp
